eth2/__init__.py
eth2/core.py
eth2/util.py
eth2/models/__init__.py
eth2/models/lighthouse.py
eth2/models/proposal.py
eth2/providers/__init__.py
eth2/providers/http.py
eth2-0.0.5.dist-info/LICENSE
eth2-0.0.5.dist-info/METADATA
eth2-0.0.5.dist-info/WHEEL
eth2-0.0.5.dist-info/top_level.txt
eth2-0.0.5.dist-info/RECORD
