Metadata-Version: 2.1
Name: eth2
Version: 0.0.5
Summary: Eth2 API
Home-page: https://github.com/protolambda/eth2.py
Author: protolambda
Author-email: proto+pip@protolambda.com
License: MIT
Keywords: eth2,ethereum,serenity,api
Platform: UNKNOWN
Classifier: Development Status :: 4 - Beta
Classifier: Intended Audience :: Developers
Classifier: License :: OSI Approved :: MIT License
Classifier: Natural Language :: English
Classifier: Programming Language :: Python :: 3
Classifier: Programming Language :: Python :: 3.8
Classifier: Programming Language :: Python :: Implementation :: PyPy
Classifier: Operating System :: OS Independent
Requires-Python: >=3.8, <4
Requires-Dist: remerkleable (>=0.1.16)
Requires-Dist: eth2spec (>=0.12.1)
Requires-Dist: trio (<0.16.0,>=0.15.0)
Requires-Dist: httpx (<0.13.0,>=0.12.1)
Provides-Extra: docs
Requires-Dist: sphinx ; extra == 'docs'
Requires-Dist: sphinx-autodoc-typehints ; extra == 'docs'
Requires-Dist: pallets-sphinx-themes ; extra == 'docs'
Requires-Dist: sphinx-issues ; extra == 'docs'
Provides-Extra: linting
Requires-Dist: flake8 ; extra == 'linting'
Provides-Extra: testing
Requires-Dist: pytest ; extra == 'testing'
